setup.py
base_bridge/__init__.py
base_bridge.egg-info/PKG-INFO
base_bridge.egg-info/SOURCES.txt
base_bridge.egg-info/dependency_links.txt
base_bridge.egg-info/top_level.txt
base_bridge.egg-info/zip-safe
base_bridge/contrib/__init__.py
base_bridge/db/__init__.py
base_bridge/db/models/__init__.py
base_bridge/db/models/decorators.py
base_bridge/db/models/fields.py
base_bridge/utils/__init__.py
base_bridge/utils/http.py
base_bridge/utils/inspect.py
base_bridge/views/__init__.py
base_bridge/views/decorators.py
base_bridge/views/generic/__init__.py