Metadata-Version: 1.1
Name: base-bridge
Version: 1.0
Summary: A base bridge between django framework and our private application.
Home-page: https://github.com/evilloop/django-base-bridge
Author: Maple.Liu
Author-email: fjliufeng@163.com
License: GNU General Public License v2 (GPLv2)
Keywords: django base bridge model field db
Platform: UNKNOWN
Classifier: License :: OSI Approved :: GNU General Public License v2 (GPLv2)
Classifier: Programming Language :: Python :: 2.7
Classifier: Intended Audience :: Developers
Classifier: Operating System :: OS Independent
Classifier: Framework :: Django
Classifier: Environment :: Web Environment
Classifier: Topic :: Internet :: WWW/HTTP
